pbpl_units/__init__.py
pbpl_units-0.1.dist-info/LICENSE
pbpl_units-0.1.dist-info/METADATA
pbpl_units-0.1.dist-info/WHEEL
pbpl_units-0.1.dist-info/top_level.txt
pbpl_units-0.1.dist-info/RECORD
