Metadata-Version: 2.1
Name: pbpl-units
Version: 0.1
Summary: foo
Author: Brian Naranjo
License: Apache-2.0
Project-URL: Homepage, https://github.com/bnara/pbpl-units
Project-URL: Changelog, https://github.com/bnara/pbpl-units/releases
Project-URL: Issues, https://github.com/bnara/pbpl-units/issues
Project-URL: CI, https://github.com/bnara/pbpl-units/actions
Classifier: License :: OSI Approved :: Apache Software License
Requires-Python: >=3.8
License-File: LICENSE
Provides-Extra: test
Requires-Dist: pytest ; extra == 'test'
